easyencryption/__init__.py
easyencryption/aes.py
easyencryption/ascii.py
easyencryption/blake.py
easyencryption/fernet.py
easyencryption/rsa.py
easyencryption/sha.py
easyencryption/shake.py
easyencryption/test_all.py
easyencryption/xor.py
easyencryption-3.1.0.0.dist-info/METADATA
easyencryption-3.1.0.0.dist-info/WHEEL
easyencryption-3.1.0.0.dist-info/top_level.txt
easyencryption-3.1.0.0.dist-info/RECORD
